cicd/__init__.py
cicd/__main__.py
cicd/config.py
cicd/driver.py
cicd/logger.py
cicd/parser.py
cicd/secret.py
cicd/archetype/__init__.py
cicd/archetype/docker.py
cicd/archetype/dropwizard.py
cicd/archetype/node.py
cicd/archetype/pip.py
cicd/archetype/store_backend.py
cicd/archetype/util.py
cicd/util/__init__.py
cicd/util/aws_util.py
cicd/util/docker_util.py
cicd/util/download_util.py
cicd/util/file_util.py
cicd/util/helm_util.py
cicd/util/maven_util.py
cicd/util/node_util.py
cicd/util/python_util.py
cicd/util/terraform_util.py
cicd/util/resources/tf_backends/s3.tf
cicd_cli-0.1.18.data/scripts/cicd
test/__init__.py
cicd_cli-0.1.18.dist-info/LICENSE
cicd_cli-0.1.18.dist-info/METADATA
cicd_cli-0.1.18.dist-info/WHEEL
cicd_cli-0.1.18.dist-info/top_level.txt
cicd_cli-0.1.18.dist-info/RECORD
