Metadata-Version: 2.1
Name: cicd-cli
Version: 0.1.18
Summary: Script for executing automated tasks
License: MIT
Classifier: License :: OSI Approved :: MIT License
Classifier: Programming Language :: Python
Classifier: Programming Language :: Python :: 3
Classifier: Programming Language :: Python :: 3.7
Requires-Python: >=3.5
License-File: LICENSE
Requires-Dist: pyyaml (>=3.0)
Requires-Dist: boto3 (>=1.16.0)
Requires-Dist: wget (>=3.0)
Requires-Dist: awscli (~=1.18.207)
